module/__init__.py
module/sosilogikk.py
sosilogikk-1.0.16.dist-info/LICENSE
sosilogikk-1.0.16.dist-info/METADATA
sosilogikk-1.0.16.dist-info/WHEEL
sosilogikk-1.0.16.dist-info/top_level.txt
sosilogikk-1.0.16.dist-info/RECORD
