Metadata-Version: 2.1
Name: sosilogikk
Version: 1.0.16
Summary: Logikk for å bruke Python biblioteker som Geopandas, Shapely, Fiona etc på .SOS-filer. sosilogikk.py i mappen modules definerer en logikk for å bryte opp en .SOS-fil i objektsegmenter som kan lastes inn i en Geopandas dataframe.
Home-page: https://github.com/jesperfjellin/sosilogikk
Author: Jesper Fjellin
Author-email: jesperfjellin@gmail.com
License: GPLv3
Classifier: Programming Language :: Python :: 3
Classifier: License :: OSI Approved :: MIT License
Classifier: Operating System :: OS Independent
Requires-Python: >=3.6
License-File: LICENSE
Requires-Dist: geopandas ==1.0.1
Requires-Dist: numpy ==1.26.4
Requires-Dist: pandas ==2.2.2
Requires-Dist: Shapely ==2.0.5
